ecommercetools/advertising/__init__.py
ecommercetools/advertising/advertising.py
ecommercetools/customers/__init__.py
ecommercetools/customers/customers.py
ecommercetools/marketing/__init__.py
ecommercetools/marketing/marketing.py
ecommercetools/nlp/__init__.py
ecommercetools/nlp/nlp.py
ecommercetools/operations/__init__.py
ecommercetools/operations/operations.py
ecommercetools/products/__init__.py
ecommercetools/products/products.py
ecommercetools/reports/__init__.py
ecommercetools/reports/reports.py
ecommercetools/seo/__init__.py
ecommercetools/seo/google_autocomplete.py
ecommercetools/seo/google_knowledge_graph.py
ecommercetools/seo/google_pagespeed_insights.py
ecommercetools/seo/google_search.py
ecommercetools/seo/google_search_console.py
ecommercetools/seo/robots.py
ecommercetools/seo/scraping.py
ecommercetools/seo/sitemaps.py
ecommercetools/seo/testing.py
ecommercetools/transactions/__init__.py
ecommercetools/transactions/transactions.py
ecommercetools/utilities/__init__.py
ecommercetools/utilities/metrics.py
ecommercetools/utilities/tools.py
ecommercetools-0.42.9.dist-info/LICENSE.txt
ecommercetools-0.42.9.dist-info/METADATA
ecommercetools-0.42.9.dist-info/WHEEL
ecommercetools-0.42.9.dist-info/top_level.txt
ecommercetools-0.42.9.dist-info/RECORD
