Metadata-Version: 2.1
Name: ecommercetools
Version: 0.42.9
Summary: EcommerceTools is a data science toolkit for ecommerce, marketing science, and Python SEO.
Home-page: https://github.com/practical-data-science/ecommercetools
Author: Matt Clarke
Author-email: matt@practicaldatascience.co.uk
License: MIT
Download-URL: https://github.com/practical-data-science/ecommercetools/archive/master.zip
Keywords: ecommerce,marketing,seo,seo testing,customers,products,rfm,abc,operations,analytics,python,python seo,pandas,nlp,causal impact
Platform: UNKNOWN
Classifier: Development Status :: 3 - Alpha
Classifier: Intended Audience :: Developers
Classifier: Topic :: Software Development :: Libraries :: Python Modules
Classifier: License :: OSI Approved :: MIT License
Classifier: Programming Language :: Python :: 3.6
Requires-Dist: gapandas
Requires-Dist: httplib2 (>=0.15.0)
Requires-Dist: lifetimes
Requires-Dist: numpy
Requires-Dist: pandas
Requires-Dist: pycausalimpact
Requires-Dist: requests
Requires-Dist: requests-html
Requires-Dist: sklearn
Requires-Dist: torch
Requires-Dist: transformers
